nypi/__init__.py
nypi-1.0.1.dist-info/LICENSE
nypi-1.0.1.dist-info/METADATA
nypi-1.0.1.dist-info/WHEEL
nypi-1.0.1.dist-info/top_level.txt
nypi-1.0.1.dist-info/zip-safe
nypi-1.0.1.dist-info/RECORD
