Metadata-Version: 2.1
Name: nypi
Version: 1.0.1
Summary: nypi
Home-page: UNKNOWN
Author: Natalie Fearnley
Author-email: nfearnley@gmail.com
License: MIT
Project-URL: Source, https://github.com/nfearnley/nypi
Project-URL: Tracker, https://github.com/nfearnley/nypi/issues
Platform: any
Classifier: Programming Language :: Python :: 3.9
Classifier: Operating System :: OS Independent
Classifier: License :: OSI Approved :: MIT License
Requires-Python: >=3.9
License-File: LICENSE
Requires-Dist: requests (==2.26.0)
Requires-Dist: requests-cache (==0.8.1)
Provides-Extra: dev
Requires-Dist: pytest (==6.2.5) ; extra == 'dev'
Requires-Dist: flake8 (==3.9.2) ; extra == 'dev'
Requires-Dist: autopep8 (==1.5.7) ; extra == 'dev'
